weaver/__init__.py
weaver/train.py
weaver/nn/__init__.py
weaver/nn/loss/__init__.py
weaver/nn/loss/focal.py
weaver/nn/model/ParticleNeXt.py
weaver/nn/model/ParticleNet.py
weaver/nn/model/ParticleTransformer.py
weaver/nn/model/__init__.py
weaver/utils/__init__.py
weaver/utils/dataset.py
weaver/utils/flops_counter.py
weaver/utils/import_tools.py
weaver/utils/logger.py
weaver/utils/lr_finder.py
weaver/utils/data/__init__.py
weaver/utils/data/config.py
weaver/utils/data/fileio.py
weaver/utils/data/preprocess.py
weaver/utils/data/tools.py
weaver/utils/nn/__init__.py
weaver/utils/nn/metrics.py
weaver/utils/nn/tools.py
weaver/utils/nn/optimizer/__init__.py
weaver/utils/nn/optimizer/lookahead.py
weaver/utils/nn/optimizer/radam.py
weaver/utils/nn/optimizer/ranger.py
weaver_core-0.4.17.dist-info/LICENSE
weaver_core-0.4.17.dist-info/METADATA
weaver_core-0.4.17.dist-info/WHEEL
weaver_core-0.4.17.dist-info/entry_points.txt
weaver_core-0.4.17.dist-info/top_level.txt
weaver_core-0.4.17.dist-info/RECORD
