Metadata-Version: 2.1
Name: weaver-core
Version: 0.4.17
Summary: A streamlined deep-learning framework for high energy physics
Home-page: https://github.com/hqucms/weaver-core
Author: H. Qu, C. Li
Classifier: Operating System :: OS Independent
Classifier: Programming Language :: Python
Classifier: Programming Language :: Python :: 3
Classifier: Programming Language :: Python :: 3.7
Classifier: Topic :: Scientific/Engineering
Classifier: Topic :: Scientific/Engineering :: Physics
Requires-Python: >=3.7
License-File: LICENSE
